[
  {
    "id": 1773023156481,
    "date": "2026-03-09T02:25:56.481Z",
    "title": "1w 04 인들이 필요한 이유. 결핍의 이유",
    "pages": [
      {
        "pageLabel": "1w13p",
        "blocks": [
          {
            "type": "text",
            "content": "04 인들이 필요한 이유\n결핍의 이유"
          },
          {
            "type": "text",
            "content": "왜 피곤한 것일까? 왜 우리는 여전히 부족하고 갈증이 심한 것일까? 도대체 인간은 어떤 존재이길래 이런 현상을 겪는 것일까? 이같은 질문들을 이해하기 위하여 먼저 인간 존재의 기원부터 살펴볼 필요가 있습니다. 우선 성경은 인간의 시작을 빅뱅(Big Bang)처럼 우주적 변동과 같은 시간을 오랫동안 거치며 형성된 생물체가 되었다는 진화론과 달리 하나님이 인간을 창조하셨다고 말합니다."
          },
          {
            "type": "text",
            "content": "\"하나님이 자기 형상 곧 하나님의 형상대로 사람을 창조하시되 남자와 여자를 창조하시고\"(창세기 1:27)"
          },
          {
            "type": "text",
            "content": "하나님이 인간을 창조하셨다는 말은 우리가 피조물이라는 뜻입니다. 즉 하나님처럼 스스로 존재하는 존재가 아니라 의존적인 존재라는 말입니다. 일단 이것은 사실입니다. 우리가 스스로 존재할 수 있는 존재가 아니라는 것은 수많은 질병에 의해서도 경험하지만 최종적으로 죽음을 피할 수 없다는 것만으로도 알 수 있습니다.\n\n사실 인류 역사를 보면 사람들은 이같은 죽음의 문제를 해결하고자 많은 노력을 기울였습니다. 하지만 알아낼 수 없었습니다. 고작 사람들이 깨달은 것(覺)은 싯달타 슐로몬이 도로한 것처럼 \"아무 것도 아닌\"(無)과 \"덧 비어있는 것의 체험\"(空)이 전부였습니다. 무엇인가 알 수 있는 결핍된 존재란 말입니다. 언젠가 부족했다는 말입니다. 도대체 사람은 어떤 존재이길래 이런 일이 벌어지는 것일까?"
          },
          {
            "type": "text",
            "content": "인간이란 존재"
          },
          {
            "type": "text",
            "content": "성경은 인간이 세 요소로 형성되어 있다고 가르치는데, 사도 바울은 매우 정확하게 \"영과 혼과 몸\"(살전5:23)이라고 표현하였습니다."
          },
          {
            "type": "text",
            "content": "그런데 재미있는 것은 개나 소 같은 동물과의 차이입니다. 분명히"
          }
        ]
      },
      {
        "pageLabel": "1w14p",
        "blocks": [
          {
            "type": "text",
            "content": "인간은 동물과 다릅니다. 이것은 다름에 대하여 창세기는 매우 중요한 설명을 합니다.\n\n\"하나님의 형상대로 사람을 창조하시다.\"(창세기 1:27)\n\n하나님의 형상대로 창조하였다는 말이 무엇인지 자세히 알 수 없지만 하나님의 창조 이야기에는 특별한 모서가 있습니다. 하나님이 사람에게 생기를 불어넣으심으로 \"생령\"(네페쉬 하야 חַיָּה נֶפֶשׁ)이 되었다는 기록입니다.\n\n\"여호와 하나님이 땅의 흙으로 사람을 지으시고 생기를 그 코에 불어넣으시니 사람이 생령이 되니라\"(창2:7)\n\n울흔 \"생령\"을 말하는 '네페쉬 하야'는 사람에게만 쓰이지 않고 동물들을 창조하실 때에 슨 \"생물\"이라는 표현 역시 '네페쉬 하야'를 씁니다. 그러니까 살아있는 생명체를 말할 때 씁니다. 하지만 사람은 동물처럼 단순히 창조하신 것이 아니라 그 코에 \"생기\" 곧 네사마(נְשָׁמָה)를 불어넣으심으로 사람이 되었는데, 그때 하나님의 영 '루아흐'(רוּחַ)가 내주하는 영적인 존재가 된 것입니다. 이처럼 하나님 우리 안에 들어와 내주하시므로 하나님의 형상을 담은 사람이 된 것입니다. 같은 '네페쉬 하야'지만 동물과 구별되는 이유입니다. 그래부터 우리는 동물과 달리 하나님과 의사소통이 가능한 존재, 곧 하나님을 인식하고 하나님을 경외하는 존재가 된 것입니다. 당연히 하나님의 영이 내주하시기 때문입니다.\n\n반면에 동물들이 하나님을 인식할 수 없는 이유는 인간과 달리 하나님의 영이 그 안에 내주하지 않기 때문입니다. 즉 하나님의 형상대로 지을 받은 피조물이 아니기 때문입니다. 그래서 개나 돼지등 동물은 하나님을 구하거나 종교적인 삶을 추구하지 못합니다. 영적이지 않기 때문입니다. 그러니까 곧이 표현하면 동물은 영이 없는 혼과 몸으로만 이루어졌다고 표현하는 것이 맞습니다.\n\n[THIS IS FIGURE: A simple circle diagram divided in half, with Korean text \"영/Spirit\" and \"혼/Soul\" on the left side, and \"몸/Body\" on the right side]\n\n그러므로 인간은 하나님의 영이 내주할 상태로 있어야 비로소 인간인 것이고 하나님의 영이 내주하심이 없을 때는 그냥 평범한 동물적 인간이 되는 것입니다. 요한계시록의 언어로 말하면 \"살았다 하는 이름은 가졌으나\n\n- 14 -"
          }
        ]
      },
      {
        "pageLabel": "1w15p",
        "blocks": [
          {
            "type": "text",
            "content": "죽은 자\"(계3:1)인 것입니다. 하나님의 영(루아흐)이 거하지 않기 때문입니다. 그리고 성경이 말하는 진정한 죽음은 하나님을 거두어간 상태로 현래인간의 본질인 \"먼지\"(아파르‐עפר)로 돌아가는 것입니다."
          },
          {
            "type": "text",
            "content": "\"주께서 복을 숨기신즉 그들이 떨고 주께서 그들의 호흡(루아흐)을 거두신즉 그들은 죽어 먼지(아파르)로 돌아가나이다\"(시편 104:29)"
          },
          {
            "type": "text",
            "content": "이같이 하나님의 영이 내주하지 않은 채로 만나는 죽음(첫째 사망)을 성경을 \"돌째 사망\"(계20:14)이라고 말하는 이유입니다. 하나님의 영이 내주하지 않는 자의 죽음은 언지로의 소멸이기 때문입니다. 이같은 인간 이해를 중심으로 처와 죽음을 살피겠습니다. 당연히 처음 사람을 창조과 최초의 인간인 아담과 하와 기록을 봐야 합니다."
          },
          {
            "type": "text",
            "content": "결핍 때문에"
          },
          {
            "type": "text",
            "content": "하나님이 에덴동산을 만드시고 남자와 여자를 창조하였습니다. 그리고 동산 중앙에 선악과나무와 생명나무를 심으셨는데, 선악과를 따먹는 것은 금지되었습니다. 그런데 사람들이 그 열매를 따먹습니다. 그로인해 아담과 하와는 에덴동산에서 쫓겨났을 뿐 아니라 죽음에 이르는 존재가 됩니다. 이것이 우리가 알고 있는 선악과나무 사건의 전부입니다."
          },
          {
            "type": "text",
            "content": "여기서 질문이 생깁니다. '왜 따먹었는가?'하는 것입니다. 분명히 동산 중앙에는 생명나무도 있었습니다. 그것을 먹으면 영원히 죽지 않고 살수 있었습니다.(창3:22) 하지만 아담과 하와는 생명나무에는 관심이 없었습니다. 그들은 선악과에 우선적인 관심을 보였고, 결국 따먹습니다. 그렇다면 왜 그렇게 생동한 것입니까? 영원한 생명을 얻는 것보다 더 강력한 무것이 선악과에 있었던 것입니까? 재미있게도 성경은 선악과를 따 먹은 동기에 대하여 \"하나님과 같이 된다\"(창3:5)는 뱀의 유혹으로 설명합니다."
          },
          {
            "type": "text",
            "content": "\"너희가 그것을 먹는 날에는 너희 눈이 밝아져 하나님과 같이 되어 선악을 알 줄 하나님이 아심이니라\"(창세기 3:5)"
          },
          {
            "type": "text",
            "content": "그러니까 선악과를 따 먹은 이유는 하나님과 같이 되고 싶어하는데서 시작되었다는 설명입니다. 우리는 이것을 여러 가지로 해석할 수 있겠지만 한 가지 분명한 것은 피조물된, 곧 '결핍'에서 벗어나고 싶은 강력한 욕망 때문이었습니다. 피조물로서 계속되는 근원적이고 채워지지 않는 욕망과 결핍 그리고 부족함같은 것을 채우고 싶었던 것입니다.\n\n고백록을 쓴 어거스틴 역시 그랬습니다. 그는 육체적인 쾌락과 만족을 추구하였고 마니교에 심취한 삶을 살았습니다. 하지만 그의 결핍을 해결하지 못하였었습니다. 그리고 무한히 욕망 하였지만 해결되지 않던 그가 어"
          }
        ]
      },
      {
        "pageLabel": "1w16p",
        "blocks": [
          {
            "type": "text",
            "content": "느낌 알라는 정현에서 회실의 경험을 하게 되는데, 그 순간 은전한 평화와 만족을 누립니다. 그것을 어거스틴은 고백록의 첫 페이지에 적습니다."
          },
          {
            "type": "text",
            "content": "\"당신은 우리를 당신을 향해서(ad te) 살도록 창조하셨으므로 우리 마음이 당신 안에서(in te) 안식할 때까지는 편안하지 않습니다.\"(고백록, 1.1.1)"
          },
          {
            "type": "text",
            "content": "하지만 아담과 하와는 컬립을 채우는 방법을 하나님에게서 분리되어 독립하는 것에서 찾은 것입니다. 뱀의 속삭임을 들으면서 하나님과 같이 될 수 있다 곧 나님에게 의존하지 않고 스스로 살 수 있는 자존적 존재인 하나님이 될 수 있다고 생각한 것입니다. 그럼으로 그리다면 우리 마음의 보좌에 계신 하나님을 내어쫓게 분리시키는 행위였습니다."
          },
          {
            "type": "text",
            "content": "물론 그 순간 독립적인 존재가 되었지만 하나님으로부터의 단절 곧 분리의 결과는 죽음이었습니다. 이미 하나님이 하신 말씀이었습니다."
          },
          {
            "type": "text",
            "content": "\"선악을 알게 하는 나무의 열매는 먹지 말라 네가 먹는 날에는 반드시 죽으리라\"(창2:17)"
          },
          {
            "type": "text",
            "content": "히브리적 사고에서 죽음은 하나님과의 분리를 의미합니다. 그런 의미에서 죽는 하나님과 분리된 상태를 말합니다."
          },
          {
            "type": "text",
            "content": "\"오직 너희 죄악이 너희와 너희 하나님 사이를 갈라 놓았고\"(사 59:2)"
          },
          {
            "type": "text",
            "content": "지금까지 살펴 것을 정리하면 영과 혼과 육을 가진 존재인 인간이 원래 본질은 먼지(아파르)이지만 그 코에 \"생기\" 곧 네샤마(נשמה)를 불어넣으심으로 하나님의 엄 '루아흐'(רוּחַ)가 내주하는 영적인 존재가 된 것입니다. 이것이 살아있는 상태입니다. 하지만 선악과 사건이 의미하듯 인간이 스스로 하나님과 분리되어 나오는 순간 하나님의 영이 거하지 않은 존재, 곧 하나님으로부터 분리된 상태 곧 죽음에 이른 것입니다. 그래서 야고보서 2장 26절에서 '영(히/루아흐, 헬/프뉴마, 영/spirit)이 없는 몸은 죽은 것'이"
          }
        ]
      },
      {
        "pageLabel": "1w17p",
        "blocks": [
          {
            "type": "text",
            "content": "라고 말한 이유입니다. 지금 살아있지 않나고 반문할지 모릅니다. 올른 당장 육체가 죽은 상태가 아닙니다. 하지만 성경이 그 상태를 \"살았다 하는 이름은 가졌으나 죽은 지\"(계3:1)라고 말한 이유입니다.\n\n불안의 이유\n\n어린 조카 영식이를 잠시 돌본 적이 있었습니다. 장시동안 영식이는 고무튜브 나와 잘 놀았습니다. 약간의 위기가 있었지만 그때마다 맞있는 것을 사주거나 장난감을 사주면 되었습니다. 그런데 일식적이었습니다. 어느 순간부터인가 그 어떤 것으로도 영식이의 울음을 막을 수 없는 상황이 벌어진 것입니다. 영식이는 그저 엄마를 찾으면서 죽을 것 같이 울다가 자다가를 반복하였습니다. 내가 어떻게 할 수 있는 불가능한 상황이었습니다. 그러던 영식이가 울음을 멈춘 것은 자기 어머니가 찾을 때였습니다.\n\n영식이의 고통을 걷나게 하는 것은 어머니 밖에 없었습니다. 다른 것으로는 불가능했습니다. 설령할 수 있는 현상이었습니다. 인간의 근원적인 고통과 피곤함도 마찬가지입니다. 그 어떤 쾌락도, 실지어 크닫적인 악을 사용할 즐거움도 인간의 근원적인 공허를 채울 수는 없습니다.\n\n영식이와 어머니의 관계처럼 인간이 하나님에게서 온 존재라면 하나님 외에는 이 공허와 결핍이 채워질 길은 없습니다. 그런데 문제는 하나님 없이 사는 것입니다. 성경이 말하는 죄입니다.\n\n*묵상질문\n1. 이제 죄가 무엇이며, 죽음은 무엇인지 정리해서 적어보십시오.\n\n2. 하나님 없이 인간은 불안합니다. 불안하기 때문에 인간은 그 불안을 채우기 위해 욕망합니다. 그것이 세상의 문명을 발전시키는 요소가 되기도 하였지만 그 어떤 추구도 인간을 만족시키지 못하였습니다. 어떻게 생각하십니까?"
          }
        ]
      }
    ],
    "allBlocks": [
      {
        "type": "text",
        "content": "04 인들이 필요한 이유\n결핍의 이유"
      },
      {
        "type": "text",
        "content": "왜 피곤한 것일까? 왜 우리는 여전히 부족하고 갈증이 심한 것일까? 도대체 인간은 어떤 존재이길래 이런 현상을 겪는 것일까? 이같은 질문들을 이해하기 위하여 먼저 인간 존재의 기원부터 살펴볼 필요가 있습니다. 우선 성경은 인간의 시작을 빅뱅(Big Bang)처럼 우주적 변동과 같은 시간을 오랫동안 거치며 형성된 생물체가 되었다는 진화론과 달리 하나님이 인간을 창조하셨다고 말합니다."
      },
      {
        "type": "text",
        "content": "\"하나님이 자기 형상 곧 하나님의 형상대로 사람을 창조하시되 남자와 여자를 창조하시고\"(창세기 1:27)"
      },
      {
        "type": "text",
        "content": "하나님이 인간을 창조하셨다는 말은 우리가 피조물이라는 뜻입니다. 즉 하나님처럼 스스로 존재하는 존재가 아니라 의존적인 존재라는 말입니다. 일단 이것은 사실입니다. 우리가 스스로 존재할 수 있는 존재가 아니라는 것은 수많은 질병에 의해서도 경험하지만 최종적으로 죽음을 피할 수 없다는 것만으로도 알 수 있습니다.\n\n사실 인류 역사를 보면 사람들은 이같은 죽음의 문제를 해결하고자 많은 노력을 기울였습니다. 하지만 알아낼 수 없었습니다. 고작 사람들이 깨달은 것(覺)은 싯달타 슐로몬이 도로한 것처럼 \"아무 것도 아닌\"(無)과 \"덧 비어있는 것의 체험\"(空)이 전부였습니다. 무엇인가 알 수 있는 결핍된 존재란 말입니다. 언젠가 부족했다는 말입니다. 도대체 사람은 어떤 존재이길래 이런 일이 벌어지는 것일까?"
      },
      {
        "type": "text",
        "content": "인간이란 존재"
      },
      {
        "type": "text",
        "content": "성경은 인간이 세 요소로 형성되어 있다고 가르치는데, 사도 바울은 매우 정확하게 \"영과 혼과 몸\"(살전5:23)이라고 표현하였습니다."
      },
      {
        "type": "text",
        "content": "그런데 재미있는 것은 개나 소 같은 동물과의 차이입니다. 분명히"
      },
      {
        "type": "text",
        "content": "인간은 동물과 다릅니다. 이것은 다름에 대하여 창세기는 매우 중요한 설명을 합니다.\n\n\"하나님의 형상대로 사람을 창조하시다.\"(창세기 1:27)\n\n하나님의 형상대로 창조하였다는 말이 무엇인지 자세히 알 수 없지만 하나님의 창조 이야기에는 특별한 모서가 있습니다. 하나님이 사람에게 생기를 불어넣으심으로 \"생령\"(네페쉬 하야 חַיָּה נֶפֶשׁ)이 되었다는 기록입니다.\n\n\"여호와 하나님이 땅의 흙으로 사람을 지으시고 생기를 그 코에 불어넣으시니 사람이 생령이 되니라\"(창2:7)\n\n울흔 \"생령\"을 말하는 '네페쉬 하야'는 사람에게만 쓰이지 않고 동물들을 창조하실 때에 슨 \"생물\"이라는 표현 역시 '네페쉬 하야'를 씁니다. 그러니까 살아있는 생명체를 말할 때 씁니다. 하지만 사람은 동물처럼 단순히 창조하신 것이 아니라 그 코에 \"생기\" 곧 네사마(נְשָׁמָה)를 불어넣으심으로 사람이 되었는데, 그때 하나님의 영 '루아흐'(רוּחַ)가 내주하는 영적인 존재가 된 것입니다. 이처럼 하나님 우리 안에 들어와 내주하시므로 하나님의 형상을 담은 사람이 된 것입니다. 같은 '네페쉬 하야'지만 동물과 구별되는 이유입니다. 그래부터 우리는 동물과 달리 하나님과 의사소통이 가능한 존재, 곧 하나님을 인식하고 하나님을 경외하는 존재가 된 것입니다. 당연히 하나님의 영이 내주하시기 때문입니다.\n\n반면에 동물들이 하나님을 인식할 수 없는 이유는 인간과 달리 하나님의 영이 그 안에 내주하지 않기 때문입니다. 즉 하나님의 형상대로 지을 받은 피조물이 아니기 때문입니다. 그래서 개나 돼지등 동물은 하나님을 구하거나 종교적인 삶을 추구하지 못합니다. 영적이지 않기 때문입니다. 그러니까 곧이 표현하면 동물은 영이 없는 혼과 몸으로만 이루어졌다고 표현하는 것이 맞습니다.\n\n[THIS IS FIGURE: A simple circle diagram divided in half, with Korean text \"영/Spirit\" and \"혼/Soul\" on the left side, and \"몸/Body\" on the right side]\n\n그러므로 인간은 하나님의 영이 내주할 상태로 있어야 비로소 인간인 것이고 하나님의 영이 내주하심이 없을 때는 그냥 평범한 동물적 인간이 되는 것입니다. 요한계시록의 언어로 말하면 \"살았다 하는 이름은 가졌으나\n\n- 14 -"
      },
      {
        "type": "text",
        "content": "죽은 자\"(계3:1)인 것입니다. 하나님의 영(루아흐)이 거하지 않기 때문입니다. 그리고 성경이 말하는 진정한 죽음은 하나님을 거두어간 상태로 현래인간의 본질인 \"먼지\"(아파르‐עפר)로 돌아가는 것입니다."
      },
      {
        "type": "text",
        "content": "\"주께서 복을 숨기신즉 그들이 떨고 주께서 그들의 호흡(루아흐)을 거두신즉 그들은 죽어 먼지(아파르)로 돌아가나이다\"(시편 104:29)"
      },
      {
        "type": "text",
        "content": "이같이 하나님의 영이 내주하지 않은 채로 만나는 죽음(첫째 사망)을 성경을 \"돌째 사망\"(계20:14)이라고 말하는 이유입니다. 하나님의 영이 내주하지 않는 자의 죽음은 언지로의 소멸이기 때문입니다. 이같은 인간 이해를 중심으로 처와 죽음을 살피겠습니다. 당연히 처음 사람을 창조과 최초의 인간인 아담과 하와 기록을 봐야 합니다."
      },
      {
        "type": "text",
        "content": "결핍 때문에"
      },
      {
        "type": "text",
        "content": "하나님이 에덴동산을 만드시고 남자와 여자를 창조하였습니다. 그리고 동산 중앙에 선악과나무와 생명나무를 심으셨는데, 선악과를 따먹는 것은 금지되었습니다. 그런데 사람들이 그 열매를 따먹습니다. 그로인해 아담과 하와는 에덴동산에서 쫓겨났을 뿐 아니라 죽음에 이르는 존재가 됩니다. 이것이 우리가 알고 있는 선악과나무 사건의 전부입니다."
      },
      {
        "type": "text",
        "content": "여기서 질문이 생깁니다. '왜 따먹었는가?'하는 것입니다. 분명히 동산 중앙에는 생명나무도 있었습니다. 그것을 먹으면 영원히 죽지 않고 살수 있었습니다.(창3:22) 하지만 아담과 하와는 생명나무에는 관심이 없었습니다. 그들은 선악과에 우선적인 관심을 보였고, 결국 따먹습니다. 그렇다면 왜 그렇게 생동한 것입니까? 영원한 생명을 얻는 것보다 더 강력한 무것이 선악과에 있었던 것입니까? 재미있게도 성경은 선악과를 따 먹은 동기에 대하여 \"하나님과 같이 된다\"(창3:5)는 뱀의 유혹으로 설명합니다."
      },
      {
        "type": "text",
        "content": "\"너희가 그것을 먹는 날에는 너희 눈이 밝아져 하나님과 같이 되어 선악을 알 줄 하나님이 아심이니라\"(창세기 3:5)"
      },
      {
        "type": "text",
        "content": "그러니까 선악과를 따 먹은 이유는 하나님과 같이 되고 싶어하는데서 시작되었다는 설명입니다. 우리는 이것을 여러 가지로 해석할 수 있겠지만 한 가지 분명한 것은 피조물된, 곧 '결핍'에서 벗어나고 싶은 강력한 욕망 때문이었습니다. 피조물로서 계속되는 근원적이고 채워지지 않는 욕망과 결핍 그리고 부족함같은 것을 채우고 싶었던 것입니다.\n\n고백록을 쓴 어거스틴 역시 그랬습니다. 그는 육체적인 쾌락과 만족을 추구하였고 마니교에 심취한 삶을 살았습니다. 하지만 그의 결핍을 해결하지 못하였었습니다. 그리고 무한히 욕망 하였지만 해결되지 않던 그가 어"
      },
      {
        "type": "text",
        "content": "느낌 알라는 정현에서 회실의 경험을 하게 되는데, 그 순간 은전한 평화와 만족을 누립니다. 그것을 어거스틴은 고백록의 첫 페이지에 적습니다."
      },
      {
        "type": "text",
        "content": "\"당신은 우리를 당신을 향해서(ad te) 살도록 창조하셨으므로 우리 마음이 당신 안에서(in te) 안식할 때까지는 편안하지 않습니다.\"(고백록, 1.1.1)"
      },
      {
        "type": "text",
        "content": "하지만 아담과 하와는 컬립을 채우는 방법을 하나님에게서 분리되어 독립하는 것에서 찾은 것입니다. 뱀의 속삭임을 들으면서 하나님과 같이 될 수 있다 곧 나님에게 의존하지 않고 스스로 살 수 있는 자존적 존재인 하나님이 될 수 있다고 생각한 것입니다. 그럼으로 그리다면 우리 마음의 보좌에 계신 하나님을 내어쫓게 분리시키는 행위였습니다."
      },
      {
        "type": "text",
        "content": "물론 그 순간 독립적인 존재가 되었지만 하나님으로부터의 단절 곧 분리의 결과는 죽음이었습니다. 이미 하나님이 하신 말씀이었습니다."
      },
      {
        "type": "text",
        "content": "\"선악을 알게 하는 나무의 열매는 먹지 말라 네가 먹는 날에는 반드시 죽으리라\"(창2:17)"
      },
      {
        "type": "text",
        "content": "히브리적 사고에서 죽음은 하나님과의 분리를 의미합니다. 그런 의미에서 죽는 하나님과 분리된 상태를 말합니다."
      },
      {
        "type": "text",
        "content": "\"오직 너희 죄악이 너희와 너희 하나님 사이를 갈라 놓았고\"(사 59:2)"
      },
      {
        "type": "text",
        "content": "지금까지 살펴 것을 정리하면 영과 혼과 육을 가진 존재인 인간이 원래 본질은 먼지(아파르)이지만 그 코에 \"생기\" 곧 네샤마(נשמה)를 불어넣으심으로 하나님의 엄 '루아흐'(רוּחַ)가 내주하는 영적인 존재가 된 것입니다. 이것이 살아있는 상태입니다. 하지만 선악과 사건이 의미하듯 인간이 스스로 하나님과 분리되어 나오는 순간 하나님의 영이 거하지 않은 존재, 곧 하나님으로부터 분리된 상태 곧 죽음에 이른 것입니다. 그래서 야고보서 2장 26절에서 '영(히/루아흐, 헬/프뉴마, 영/spirit)이 없는 몸은 죽은 것'이"
      },
      {
        "type": "text",
        "content": "라고 말한 이유입니다. 지금 살아있지 않나고 반문할지 모릅니다. 올른 당장 육체가 죽은 상태가 아닙니다. 하지만 성경이 그 상태를 \"살았다 하는 이름은 가졌으나 죽은 지\"(계3:1)라고 말한 이유입니다.\n\n불안의 이유\n\n어린 조카 영식이를 잠시 돌본 적이 있었습니다. 장시동안 영식이는 고무튜브 나와 잘 놀았습니다. 약간의 위기가 있었지만 그때마다 맞있는 것을 사주거나 장난감을 사주면 되었습니다. 그런데 일식적이었습니다. 어느 순간부터인가 그 어떤 것으로도 영식이의 울음을 막을 수 없는 상황이 벌어진 것입니다. 영식이는 그저 엄마를 찾으면서 죽을 것 같이 울다가 자다가를 반복하였습니다. 내가 어떻게 할 수 있는 불가능한 상황이었습니다. 그러던 영식이가 울음을 멈춘 것은 자기 어머니가 찾을 때였습니다.\n\n영식이의 고통을 걷나게 하는 것은 어머니 밖에 없었습니다. 다른 것으로는 불가능했습니다. 설령할 수 있는 현상이었습니다. 인간의 근원적인 고통과 피곤함도 마찬가지입니다. 그 어떤 쾌락도, 실지어 크닫적인 악을 사용할 즐거움도 인간의 근원적인 공허를 채울 수는 없습니다.\n\n영식이와 어머니의 관계처럼 인간이 하나님에게서 온 존재라면 하나님 외에는 이 공허와 결핍이 채워질 길은 없습니다. 그런데 문제는 하나님 없이 사는 것입니다. 성경이 말하는 죄입니다.\n\n*묵상질문\n1. 이제 죄가 무엇이며, 죽음은 무엇인지 정리해서 적어보십시오.\n\n2. 하나님 없이 인간은 불안합니다. 불안하기 때문에 인간은 그 불안을 채우기 위해 욕망합니다. 그것이 세상의 문명을 발전시키는 요소가 되기도 하였지만 그 어떤 추구도 인간을 만족시키지 못하였습니다. 어떻게 생각하십니까?"
      }
    ],
    "questions": [
      {
        "q": "1. 이제 죄가 무엇이며, 죽음은 무엇인지 정리해서 적어보십시오.",
        "a": ""
      },
      {
        "q": "2. 하나님 없이 인간은 불안합니다. 불안하기 때문에 인간은 그 불안을 채우기 위해 욕망합니다. 그것이 세상의 문명을 발전시키는 요소가 되기도 하였지만 그 어떤 추구도 인간을 만족시키지 못하였습니다. 어떻게 생각하십니까?",
        "a": ""
      }
    ]
  },
  {
    "id": 1772939407337,
    "date": "2026-03-08T03:10:07.337Z",
    "title": "1w 03 믿음이 필요한 이유. 피곤한 이유",
    "pages": [
      {
        "pageLabel": "1w9p",
        "blocks": [
          {
            "type": "text",
            "content": "03 믿음이 필요한 이유\n피곤한 이유"
          },
          {
            "type": "text",
            "content": "왜 사람들은 먹추지 못하는 것일까? 왜 그 꿈을 불안한 시간의 여유도 없는 것입니까? 왜 알면서도 그런은 싫을 계속 사는 것입니까? '시지프스 신화'에서 알베르트 까뮈 역시 같은 질문을 던집니다. 시지프스가 산꼭대기로 바위를 밀어 올리지만, 정상에 이르면 바위는 다시 아래로 굴러 떨어지는 것을 반복되는 것을 알면서도 반복을 멈추지 않는 모습은 '부조리'('L'Absurde) 자체입니다."
          },
          {
            "type": "text",
            "content": "이같은 싫을 반복합니다. 예외는 없습니다."
          },
          {
            "type": "text",
            "content": "까뮈는 이 부조리를 중식시키는 방법으로 그것에 순응하며 그저 사"
          }
        ]
      },
      {
        "pageLabel": "1w10p",
        "blocks": [
          {
            "type": "text",
            "content": "는 것이 아니라 부조리를 똑바로 응시하며 반항하는 것이 인간의 존엄이라고 말을 하였습니다. 그 방법 중의 하나가 인생을 직시하며 사유하며 사는 것입니다.\n\n무(無)와 공(空)으로 갑니다\n\n그렇게 산 사람들 중의 한 사람이 불교의 창시자인 싯달타입니다. 태어나면서부터 왕자인 그는 어느 날 죽어가는 장례 행렬 앞에서 그저 주어진 대로 살지않고 자신의 인생에 대해 직시하며 물음을 던지며 살기로 합니다. 하지만 그가 그렇게 시도하였던 질문에 대한 깨달음(覺)은 인생이란 무(無), 공(空)에 불과하며 아무리 노력하여도 손 바다(苦海)를 헤매는 것에 불과하다는 인식이었습니다. 한마디로 구원에 이를 수 없다는 고백이었습니다.\n\n인간적인 관점에서 볼 때 섣부르게 삶을 추구했던 사람들 중에 성철스님이 있습니다. 그런데 성철스님이 죽음을 맞두고 쓴 열반송에서 당황스러운 고백을 합니다. 사실 성철 스님은 24살에 가정을 두고 출가하였는데, 그때 그의 기개와 꿈은 대단하였습니다. 그의 꿈은 인생을 깨닫고 이 세상을 바르게 이끌고자 하는 열정이었습니다. 그것이 그가 출가한 이유였습니다. 그의 출가송은 이렇습니다.\n\n\"하늘에 가득한 큰 원도 붉은 회초불에 한 점 티끌이로다\n(滿天大紫紅爐雪)\n바다를 뒤덮는 큰 물도 밝은 햇살 아래 한 방울 이슬이로다\n누가 꿈속 같은 세상에 장차 나와 꿈만 꾸다 떠나 가랴\n만고의 진리를 찾아 나홀로 걸어 가리라\"\n\n실제로 성철 스님은 1993년 11월 4일 82세의 나이로 죽기 전까지 치열한 수행을 하였습니다. 살아가는 동안 그는 철저한 구도자의 자세와 선을 추구하였습니다. 그의 수도적 삶을 알 수 있는 것 중의 하나가 앉아서 잠을 잤다는 장좌불와(長坐不臥) 8년 수행입니다. 뿐만 아니라 그의 삶에는 그 흔한 세속적인 부도도 없었습니다. 그의 족음 앞에 남은 것이라고는 국화꽃 바구니 두 개와 벽에 걸린 낡은 장삼 그리고 쓰던 몽당연필, 편지지, 주장자(住杖子) 하나가 전부였습니다. 그런데 이 엄청난 구도자의 삶을 살았던 성철 스님이 당황스러운\n열반송을 남깁니다. 출가송이 일종의 비전 선언이라면 열반송은 그 추구하던 삶을 정리하는 깨달음의 고백인데 그 내용이 이렇습니다."
          }
        ]
      },
      {
        "pageLabel": "1w11p",
        "blocks": [
          {
            "type": "text",
            "content": "\"평생에 걸쳐 남녀의 우리를 속였으니\n牛平欺就男女群\n하늘에 가득한 죄업이 수미산보다 높구나\n満天罪業過須弥\n산 채로 우간지옥에 떨어져도 한이 안 갈레나 되네\n活陥阿鼻根萬端\n한 덩이 붉은 해는 푸른 산에 걸려 있다\"\n一輪吐紅掛碧山"
          },
          {
            "type": "text",
            "content": "그의 고백은 놀랍게도 출가하면서 세운 '미천대왕'의 꿈이 '미천죄옥'으로 끝났다는 것이었습니다. 더욱이 놀라운 것은 자신의 삶이 수많은 사람을 속이는 삶이었고, 그 마지막은 결이 없는 지옥으로 떨어지는 것이 전부라고 고백한 것입니다. 물론 성철 스님의 겸손한 고백이라고 말할 수 있습니다. 하지만 마지막 두 구절이 문제입니다. 일반적으로 이 두 구절은 다음과 같이 해석합니다."
          },
          {
            "type": "text",
            "content": "\"나는 지은 죄를 안고 무간지옥에 떨어져 가지만 (사실 그는 지옥을 제도하러 갔다) 내가 바라본 푸른 산은 언제나 그대로 거기 있으니 너희들은 공부를 게을리하지 말라\""
          },
          {
            "type": "text",
            "content": "그러나 성철 스님의 말 그대로를 해석하면 이렇게 풀어 쓸 수 있습니다."
          },
          {
            "type": "text",
            "content": "\"평생동안 거짓된 가르침으로 많은 사람들에게 잘못된 가르침과 방향을 제시하였으니 그동안 내가 쌓은 죄가 수미산보다 높구나. 그러므로 살아있는 채로 고통을 당하며 끝이 없는 지옥에 떨어지게 되니 한이 만 갈레나 되네. 이 한 덩어리 붉은 해가 저기 푸른 산에 걸려있네.\""
          },
          {
            "type": "text",
            "content": "여전히 마지막 구절을 이해하기가 쉽지는 않지 한 가지 분명한 것은 성철 스님의 삶이 치열한 구도자의 삶이었다는 것입니다. 동시에 그가 깨달은 것의 길이와 진지함도 부정할 수 없습니다. 그러나 성철 스님 역시 깨달은 것(覺)은 무(無), 공(空)의 경험이었던 것입니다."
          },
          {
            "type": "text",
            "content": "인간의 본질적인 문제"
          },
          {
            "type": "text",
            "content": "한계, 알 수 없다. 우리들의 존재를 표현하는 단어는 이외에도 공허, 겁탐, 부족, 재한 등이 있습니다. 성철 스님과 같이 똑같은 예기를 적은 사람이 성경에 나오는데, 이스라엘 역사상 가장 부유하고 지혜로웠던 왕 솔로몬입니다. 그가 쓴 전도서에서 그 역시 '헛됨'이라고 표현하였습니다."
          }
        ]
      },
      {
        "pageLabel": "1w12p",
        "blocks": [
          {
            "type": "text",
            "content": "\"헛되고 헛되며 헛되고 헛되니 모든 것이 헛되도다... 내가 해 아래에서 행하는 모든 일을 보았노라 보라 모두 다 헛되어 바람을 잡으려는 것이로다\"(전도서 1:2,14))"
          },
          {
            "type": "text",
            "content": "'헛되다.' '바람을 잡으려는 것이다.' 이같은 솔로몬의 깨달음은 자신이 죽은 후에도 태양은 뜰 것이고 사람들은 일상적인 삶에 분주할 것을 인식했기 때문이었습니다."
          },
          {
            "type": "text",
            "content": "\"지혜로운 사람도 어리석은 사람과 함께 사람들의 기억에서 영원히 사라져버린다. 전에도 그랬지만 앞으로도 모든 일은 잊혀지고 말리라. 지혜로운 사람도 어리석은 사람과 함께 죽지 않는가!\"(공동번역/전도서 2:16)"
          },
          {
            "type": "text",
            "content": "아무리 친한 친구가 죽어도 우리는 곧 수다를 떨 것이고 무엇을 먹고 마실까를 고민하며 쓸데없는 관심사에 목숨을 걸고 있을 것입니다. 그것이 우리 존재입니다. 더욱이 우리는 잊고 잊혀집니다. 어떤 것도 확실한 것이 없습니다. 솔로몬이 적은 것처럼 말입니다."
          },
          {
            "type": "text",
            "content": "\"이전 세대를 기억함이 없으니 장래 세대도 그 후 세대가 기억함이 없으리라\"(전도서 1:11)"
          },
          {
            "type": "text",
            "content": "피곤한 이유"
          },
          {
            "type": "text",
            "content": "'모든 것이 헛되다.' 어느 날 이 사실을 깨닫게 되는 순간 찾아오는 것이 피곤함입니다. 시지프스 신화의 반복처럼 아무리 추구하여도 만족함이 없고 끝이 없기 때문입니다. 그래서 언제나 부족합니다. 언제나 결핍되어 있습니다. 이 끝이 없는 삶 때문에 피곤합니다. 뒷골이 땡기고 어깨가 빠근합니다. 솔로몬이 경험한 것이었습니다."
          },
          {
            "type": "text",
            "content": "\"만물의 피곤함을 사람이 말로 다 할 수 없나니 눈은 보아도 족함이 없고 귀는 들어도 차지 아니하는도다\"(전도서 1:8)"
          },
          {
            "type": "text",
            "content": "*묵상질문\n아무리 노력해도 우리에게 남는 것은 피곤할뿐입니다. 이 끝없는 삶이 피곤하지 않습니까? 여전히 부족하고 여전히 갈증나는 이유는 무엇입니까?"
          }
        ]
      }
    ],
    "allBlocks": [
      {
        "type": "text",
        "content": "03 믿음이 필요한 이유\n피곤한 이유"
      },
      {
        "type": "text",
        "content": "왜 사람들은 먹추지 못하는 것일까? 왜 그 꿈을 불안한 시간의 여유도 없는 것입니까? 왜 알면서도 그런은 싫을 계속 사는 것입니까? '시지프스 신화'에서 알베르트 까뮈 역시 같은 질문을 던집니다. 시지프스가 산꼭대기로 바위를 밀어 올리지만, 정상에 이르면 바위는 다시 아래로 굴러 떨어지는 것을 반복되는 것을 알면서도 반복을 멈추지 않는 모습은 '부조리'('L'Absurde) 자체입니다."
      },
      {
        "type": "text",
        "content": "이같은 싫을 반복합니다. 예외는 없습니다."
      },
      {
        "type": "text",
        "content": "까뮈는 이 부조리를 중식시키는 방법으로 그것에 순응하며 그저 사"
      },
      {
        "type": "text",
        "content": "는 것이 아니라 부조리를 똑바로 응시하며 반항하는 것이 인간의 존엄이라고 말을 하였습니다. 그 방법 중의 하나가 인생을 직시하며 사유하며 사는 것입니다.\n\n무(無)와 공(空)으로 갑니다\n\n그렇게 산 사람들 중의 한 사람이 불교의 창시자인 싯달타입니다. 태어나면서부터 왕자인 그는 어느 날 죽어가는 장례 행렬 앞에서 그저 주어진 대로 살지않고 자신의 인생에 대해 직시하며 물음을 던지며 살기로 합니다. 하지만 그가 그렇게 시도하였던 질문에 대한 깨달음(覺)은 인생이란 무(無), 공(空)에 불과하며 아무리 노력하여도 손 바다(苦海)를 헤매는 것에 불과하다는 인식이었습니다. 한마디로 구원에 이를 수 없다는 고백이었습니다.\n\n인간적인 관점에서 볼 때 섣부르게 삶을 추구했던 사람들 중에 성철스님이 있습니다. 그런데 성철스님이 죽음을 맞두고 쓴 열반송에서 당황스러운 고백을 합니다. 사실 성철 스님은 24살에 가정을 두고 출가하였는데, 그때 그의 기개와 꿈은 대단하였습니다. 그의 꿈은 인생을 깨닫고 이 세상을 바르게 이끌고자 하는 열정이었습니다. 그것이 그가 출가한 이유였습니다. 그의 출가송은 이렇습니다.\n\n\"하늘에 가득한 큰 원도 붉은 회초불에 한 점 티끌이로다\n(滿天大紫紅爐雪)\n바다를 뒤덮는 큰 물도 밝은 햇살 아래 한 방울 이슬이로다\n누가 꿈속 같은 세상에 장차 나와 꿈만 꾸다 떠나 가랴\n만고의 진리를 찾아 나홀로 걸어 가리라\"\n\n실제로 성철 스님은 1993년 11월 4일 82세의 나이로 죽기 전까지 치열한 수행을 하였습니다. 살아가는 동안 그는 철저한 구도자의 자세와 선을 추구하였습니다. 그의 수도적 삶을 알 수 있는 것 중의 하나가 앉아서 잠을 잤다는 장좌불와(長坐不臥) 8년 수행입니다. 뿐만 아니라 그의 삶에는 그 흔한 세속적인 부도도 없었습니다. 그의 족음 앞에 남은 것이라고는 국화꽃 바구니 두 개와 벽에 걸린 낡은 장삼 그리고 쓰던 몽당연필, 편지지, 주장자(住杖子) 하나가 전부였습니다. 그런데 이 엄청난 구도자의 삶을 살았던 성철 스님이 당황스러운\n열반송을 남깁니다. 출가송이 일종의 비전 선언이라면 열반송은 그 추구하던 삶을 정리하는 깨달음의 고백인데 그 내용이 이렇습니다."
      },
      {
        "type": "text",
        "content": "\"평생에 걸쳐 남녀의 우리를 속였으니\n牛平欺就男女群\n하늘에 가득한 죄업이 수미산보다 높구나\n満天罪業過須弥\n산 채로 우간지옥에 떨어져도 한이 안 갈레나 되네\n活陥阿鼻根萬端\n한 덩이 붉은 해는 푸른 산에 걸려 있다\"\n一輪吐紅掛碧山"
      },
      {
        "type": "text",
        "content": "그의 고백은 놀랍게도 출가하면서 세운 '미천대왕'의 꿈이 '미천죄옥'으로 끝났다는 것이었습니다. 더욱이 놀라운 것은 자신의 삶이 수많은 사람을 속이는 삶이었고, 그 마지막은 결이 없는 지옥으로 떨어지는 것이 전부라고 고백한 것입니다. 물론 성철 스님의 겸손한 고백이라고 말할 수 있습니다. 하지만 마지막 두 구절이 문제입니다. 일반적으로 이 두 구절은 다음과 같이 해석합니다."
      },
      {
        "type": "text",
        "content": "\"나는 지은 죄를 안고 무간지옥에 떨어져 가지만 (사실 그는 지옥을 제도하러 갔다) 내가 바라본 푸른 산은 언제나 그대로 거기 있으니 너희들은 공부를 게을리하지 말라\""
      },
      {
        "type": "text",
        "content": "그러나 성철 스님의 말 그대로를 해석하면 이렇게 풀어 쓸 수 있습니다."
      },
      {
        "type": "text",
        "content": "\"평생동안 거짓된 가르침으로 많은 사람들에게 잘못된 가르침과 방향을 제시하였으니 그동안 내가 쌓은 죄가 수미산보다 높구나. 그러므로 살아있는 채로 고통을 당하며 끝이 없는 지옥에 떨어지게 되니 한이 만 갈레나 되네. 이 한 덩어리 붉은 해가 저기 푸른 산에 걸려있네.\""
      },
      {
        "type": "text",
        "content": "여전히 마지막 구절을 이해하기가 쉽지는 않지 한 가지 분명한 것은 성철 스님의 삶이 치열한 구도자의 삶이었다는 것입니다. 동시에 그가 깨달은 것의 길이와 진지함도 부정할 수 없습니다. 그러나 성철 스님 역시 깨달은 것(覺)은 무(無), 공(空)의 경험이었던 것입니다."
      },
      {
        "type": "text",
        "content": "인간의 본질적인 문제"
      },
      {
        "type": "text",
        "content": "한계, 알 수 없다. 우리들의 존재를 표현하는 단어는 이외에도 공허, 겁탐, 부족, 재한 등이 있습니다. 성철 스님과 같이 똑같은 예기를 적은 사람이 성경에 나오는데, 이스라엘 역사상 가장 부유하고 지혜로웠던 왕 솔로몬입니다. 그가 쓴 전도서에서 그 역시 '헛됨'이라고 표현하였습니다."
      },
      {
        "type": "text",
        "content": "\"헛되고 헛되며 헛되고 헛되니 모든 것이 헛되도다... 내가 해 아래에서 행하는 모든 일을 보았노라 보라 모두 다 헛되어 바람을 잡으려는 것이로다\"(전도서 1:2,14))"
      },
      {
        "type": "text",
        "content": "'헛되다.' '바람을 잡으려는 것이다.' 이같은 솔로몬의 깨달음은 자신이 죽은 후에도 태양은 뜰 것이고 사람들은 일상적인 삶에 분주할 것을 인식했기 때문이었습니다."
      },
      {
        "type": "text",
        "content": "\"지혜로운 사람도 어리석은 사람과 함께 사람들의 기억에서 영원히 사라져버린다. 전에도 그랬지만 앞으로도 모든 일은 잊혀지고 말리라. 지혜로운 사람도 어리석은 사람과 함께 죽지 않는가!\"(공동번역/전도서 2:16)"
      },
      {
        "type": "text",
        "content": "아무리 친한 친구가 죽어도 우리는 곧 수다를 떨 것이고 무엇을 먹고 마실까를 고민하며 쓸데없는 관심사에 목숨을 걸고 있을 것입니다. 그것이 우리 존재입니다. 더욱이 우리는 잊고 잊혀집니다. 어떤 것도 확실한 것이 없습니다. 솔로몬이 적은 것처럼 말입니다."
      },
      {
        "type": "text",
        "content": "\"이전 세대를 기억함이 없으니 장래 세대도 그 후 세대가 기억함이 없으리라\"(전도서 1:11)"
      },
      {
        "type": "text",
        "content": "피곤한 이유"
      },
      {
        "type": "text",
        "content": "'모든 것이 헛되다.' 어느 날 이 사실을 깨닫게 되는 순간 찾아오는 것이 피곤함입니다. 시지프스 신화의 반복처럼 아무리 추구하여도 만족함이 없고 끝이 없기 때문입니다. 그래서 언제나 부족합니다. 언제나 결핍되어 있습니다. 이 끝이 없는 삶 때문에 피곤합니다. 뒷골이 땡기고 어깨가 빠근합니다. 솔로몬이 경험한 것이었습니다."
      },
      {
        "type": "text",
        "content": "\"만물의 피곤함을 사람이 말로 다 할 수 없나니 눈은 보아도 족함이 없고 귀는 들어도 차지 아니하는도다\"(전도서 1:8)"
      },
      {
        "type": "text",
        "content": "*묵상질문\n아무리 노력해도 우리에게 남는 것은 피곤할뿐입니다. 이 끝없는 삶이 피곤하지 않습니까? 여전히 부족하고 여전히 갈증나는 이유는 무엇입니까?"
      }
    ],
    "questions": [
      {
        "q": "아무리 노력해도 우리에게 남는 것은 피곤할뿐입니다. 이 끝없는 삶이 피곤하지 않습니까? 여전히 부족하고 여전히 갈증나는 이유는 무엇입니까?",
        "a": "헛되다 = 끝에 무언가 있을 것이라 생각하지만, 아무것도 없다. 노력에 끝에 남는게 없다. 이는 곧 헛되다.\n노력으로 무언갈 채울 수 있을 것이라 생각했지만, 그 끝에는 아무것도 없으니. 허무한 것이고. 물을 먹어도 마시지 않은 것 같은 갈증이 느껴진다."
      }
    ]
  },
  {
    "id": 1772938529354,
    "date": "2026-03-08T02:55:29.354Z",
    "title": "1w 02 믿음이 필요한 이유. 보지 못한 꽃",
    "pages": [
      {
        "pageLabel": "1w5p",
        "blocks": [
          {
            "type": "text",
            "content": "02 믿음이 필요한 이유\n보지 못한 꽃"
          },
          {
            "type": "text",
            "content": "고은 시인이 쓴 시, 중에 '그 꽃'이 있습니다. \n\n'내리갈 때 보았네/\n올라갈 때 못 본/ \n그 꽃' \n\n짧지만 강렬한 시입니다. 그런데 이 시를 읽다가\n이런 질문이 생겼습니다."
          },
          {
            "type": "text",
            "content": "'왜 올라갈 때는 그 꽃을 보지 못했을까?'"
          },
          {
            "type": "text",
            "content": "올라갈 때 보지 못한 이유는 산 정상까지 올라가는 것에만 신경을 쓰기 때문입니다. 목적을 향해 걸어가는 동안 다른 것을 생각할 겨를이 없었습니다."
          },
          {
            "type": "text",
            "content": "그러다 질문이 생겼습니다. '어디로 가는 걸까?' 가다 알고 질문이 생겼습니다. 하지만 너무 열심히 가고 있는 사람들의 모습 때문에 물어볼 용기가 생기지 않았습니다."
          }
        ]
      },
      {
        "pageLabel": "1w6p",
        "blocks": [
          {
            "type": "text",
            "content": "시간이 지날수록 조바심이 생겼습니다. 뒤쳐질까봐 두려워졌습니다. 그때부터 나도 속도를 냈습니다. 이내 그 꽃은 잊혀졌습니다."
          },
          {
            "type": "text",
            "content": "그러던 어느 날 내가 발견한 것은 정신없이 달리고 있는 나였습니다. 그 무리 속에 있는 나였습니다."
          },
          {
            "type": "text",
            "content": "끝이 없는 여행, 반복되는 삶이 그랬지만 아무리 시간이 지나갔지만 그 어느 것도 만족할만한 끝이 보이지 않았습니다. 그러다가 소식을 들었습니다. 끝에 소식이었습니다. 나보다 앞서 갔던 이들이 만난 끝에 대한 소식이었습니다."
          },
          {
            "type": "text",
            "content": "그래서 멈췄습니다."
          }
        ]
      },
      {
        "pageLabel": "1w7p",
        "blocks": [
          {
            "type": "text",
            "content": "보지 못한 꽃"
          },
          {
            "type": "text",
            "content": "어느 날 잠시 동안 올라올 때 보지 못했던 그 꽃을 보러갈까 생각도 했습니다. 하지만 그 걸음을 멈출 수 없었습니다. 조금만 더 가기로 하였습니다. 그래서 누구나 다 가는 대학을 가야 하니까, 그런데 대학이 끝이 아니었습니다. 학교 공부는 물론이지만 이상한 압박을 당했습니다. 그래서 아르바이트를 하고 시간을 내어 데이트도 했습니다. 졸업은 멀었지만 취업을 생각하고, 그것 때문에 시간을 소비하고 다행히 취업을 하였지만 끝이 아니었습니다. 계속된 삶, 결혼을 해도 끝난 것이 아니었습니다. 아이가 생겼습니다. 많은 교육비가 필요하고 회사는 더 많은 것을 요구했습니다. 당연히 승진해야 했습니다. 이미 늘어난 생활비용을 감당하려면 더 열심히 일을 해야 했습니다. 그렇다고 끝나지 않았습니다. 더 많은 것들이 기다리고 있었습니다. 마치 산을 넘으면 또 다른 산이 기다리고 있는 것 같았습니다. 첩첩 산중이었습니다."
          },
          {
            "type": "text",
            "content": "그렇게 살던 어느 날 누군가로부터 그 꽃에 대한 이야기를 들었습니다. 보고 싶었습니다. 그렇다고 해서 볼 수 있는 것이 아니었습니다. 그 꽃이 항상 거기에 있는 것은 아니었습니다."
          },
          {
            "type": "text",
            "content": "'그 꽃 2'"
          },
          {
            "type": "text",
            "content": "소문을 들었네"
          },
          {
            "type": "text",
            "content": "그 꽃"
          },
          {
            "type": "text",
            "content": "올라가면서 보려하였네\n보지 못했네"
          },
          {
            "type": "text",
            "content": "내려가면서 보려하였네\n보지 못했네"
          },
          {
            "type": "text",
            "content": "그 꽃"
          },
          {
            "type": "text",
            "content": "이미 시든걸 올랐네"
          }
        ]
      },
      {
        "pageLabel": "1w8p",
        "blocks": [
          {
            "type": "text",
            "content": "그리고 만난 것은 나 역시 시든 모습이었습니다. 더 이상 무엇을\n추구할 힘도 남아있지 않은 자신을 발견한 것입니다. 어떤 새로운 목표를\n정해서 다시 그 산으로 올라갈만한 용기도, 힘도 남아있지 않은 채 끝에 이\n른 것입니다. 그것이 인생의 끝이었습니다. 끝난 것입니다.\n\n'그 사람 2'\n\n올라가고 싶었네\n꼭 보고 싶었네\n\n그 꽃\n\n갈 수 없었네\n누워 산만 처다보았네\n\n그 사람\n그러다 산이 되었네\n\n\"모든 사람에게 임하는 그 모든 것이 일반이라 의인과 악인, 선한\n자와 깨끗한 자와 깨끗하지 아니한 자... 이 모든 것의 결국은 일반이라...\n모든 사람은 결국 죽은 자들에게로 돌아가는 것이라\"(전도서 9:2~3)\n\n*묵상질문\n모든 인간이 만나게 될 마지막 끝 죽음에 대하여 생각해본 적이 있\n습니까? 우리의 삶은 이 세상이 전부입니까? 이렇게 살다가 끝나는 것입니\n까? 어떻게 생각하십니까?\n\n- 8 -"
          }
        ]
      }
    ],
    "allBlocks": [
      {
        "type": "text",
        "content": "02 믿음이 필요한 이유\n보지 못한 꽃"
      },
      {
        "type": "text",
        "content": "고은 시인이 쓴 시, 중에 '그 꽃'이 있습니다. \n\n'내리갈 때 보았네/\n올라갈 때 못 본/ \n그 꽃' \n\n짧지만 강렬한 시입니다. 그런데 이 시를 읽다가\n이런 질문이 생겼습니다."
      },
      {
        "type": "text",
        "content": "'왜 올라갈 때는 그 꽃을 보지 못했을까?'"
      },
      {
        "type": "text",
        "content": "올라갈 때 보지 못한 이유는 산 정상까지 올라가는 것에만 신경을 쓰기 때문입니다. 목적을 향해 걸어가는 동안 다른 것을 생각할 겨를이 없었습니다."
      },
      {
        "type": "text",
        "content": "그러다 질문이 생겼습니다. '어디로 가는 걸까?' 가다 알고 질문이 생겼습니다. 하지만 너무 열심히 가고 있는 사람들의 모습 때문에 물어볼 용기가 생기지 않았습니다."
      },
      {
        "type": "text",
        "content": "시간이 지날수록 조바심이 생겼습니다. 뒤쳐질까봐 두려워졌습니다. 그때부터 나도 속도를 냈습니다. 이내 그 꽃은 잊혀졌습니다."
      },
      {
        "type": "text",
        "content": "그러던 어느 날 내가 발견한 것은 정신없이 달리고 있는 나였습니다. 그 무리 속에 있는 나였습니다."
      },
      {
        "type": "text",
        "content": "끝이 없는 여행, 반복되는 삶이 그랬지만 아무리 시간이 지나갔지만 그 어느 것도 만족할만한 끝이 보이지 않았습니다. 그러다가 소식을 들었습니다. 끝에 소식이었습니다. 나보다 앞서 갔던 이들이 만난 끝에 대한 소식이었습니다."
      },
      {
        "type": "text",
        "content": "그래서 멈췄습니다."
      },
      {
        "type": "text",
        "content": "보지 못한 꽃"
      },
      {
        "type": "text",
        "content": "어느 날 잠시 동안 올라올 때 보지 못했던 그 꽃을 보러갈까 생각도 했습니다. 하지만 그 걸음을 멈출 수 없었습니다. 조금만 더 가기로 하였습니다. 그래서 누구나 다 가는 대학을 가야 하니까, 그런데 대학이 끝이 아니었습니다. 학교 공부는 물론이지만 이상한 압박을 당했습니다. 그래서 아르바이트를 하고 시간을 내어 데이트도 했습니다. 졸업은 멀었지만 취업을 생각하고, 그것 때문에 시간을 소비하고 다행히 취업을 하였지만 끝이 아니었습니다. 계속된 삶, 결혼을 해도 끝난 것이 아니었습니다. 아이가 생겼습니다. 많은 교육비가 필요하고 회사는 더 많은 것을 요구했습니다. 당연히 승진해야 했습니다. 이미 늘어난 생활비용을 감당하려면 더 열심히 일을 해야 했습니다. 그렇다고 끝나지 않았습니다. 더 많은 것들이 기다리고 있었습니다. 마치 산을 넘으면 또 다른 산이 기다리고 있는 것 같았습니다. 첩첩 산중이었습니다."
      },
      {
        "type": "text",
        "content": "그렇게 살던 어느 날 누군가로부터 그 꽃에 대한 이야기를 들었습니다. 보고 싶었습니다. 그렇다고 해서 볼 수 있는 것이 아니었습니다. 그 꽃이 항상 거기에 있는 것은 아니었습니다."
      },
      {
        "type": "text",
        "content": "'그 꽃 2'"
      },
      {
        "type": "text",
        "content": "소문을 들었네"
      },
      {
        "type": "text",
        "content": "그 꽃"
      },
      {
        "type": "text",
        "content": "올라가면서 보려하였네\n보지 못했네"
      },
      {
        "type": "text",
        "content": "내려가면서 보려하였네\n보지 못했네"
      },
      {
        "type": "text",
        "content": "그 꽃"
      },
      {
        "type": "text",
        "content": "이미 시든걸 올랐네"
      },
      {
        "type": "text",
        "content": "그리고 만난 것은 나 역시 시든 모습이었습니다. 더 이상 무엇을\n추구할 힘도 남아있지 않은 자신을 발견한 것입니다. 어떤 새로운 목표를\n정해서 다시 그 산으로 올라갈만한 용기도, 힘도 남아있지 않은 채 끝에 이\n른 것입니다. 그것이 인생의 끝이었습니다. 끝난 것입니다.\n\n'그 사람 2'\n\n올라가고 싶었네\n꼭 보고 싶었네\n\n그 꽃\n\n갈 수 없었네\n누워 산만 처다보았네\n\n그 사람\n그러다 산이 되었네\n\n\"모든 사람에게 임하는 그 모든 것이 일반이라 의인과 악인, 선한\n자와 깨끗한 자와 깨끗하지 아니한 자... 이 모든 것의 결국은 일반이라...\n모든 사람은 결국 죽은 자들에게로 돌아가는 것이라\"(전도서 9:2~3)\n\n*묵상질문\n모든 인간이 만나게 될 마지막 끝 죽음에 대하여 생각해본 적이 있\n습니까? 우리의 삶은 이 세상이 전부입니까? 이렇게 살다가 끝나는 것입니\n까? 어떻게 생각하십니까?\n\n- 8 -"
      }
    ],
    "questions": [
      {
        "q": "모든 인간이 만나게 될 마지막 끝 죽음에 대하여 생각해본 적이 있습니까? 우리의 삶은 이 세상이 전부입니까? 이렇게 살다가 끝나는 것입니까? 어떻게 생각하십니까?",
        "a": "떠나면 하나님의 나라만 가면 된다고 생각했습니다.\n이제는 남겨 놓는 것도 고민을 해야 해서, 어떻게 해야 하나 늘 고민입니다"
      }
    ]
  },
  {
    "id": 1772885726602,
    "date": "2026-03-07T12:15:26.602Z",
    "title": "1w 01 믿음이 필요한 이유. 인생(人生)",
    "pages": [
      {
        "pageLabel": "1w1p",
        "blocks": [
          {
            "type": "text",
            "content": "01 믿음이 필요한 이유\n인생(人生)\n\n팀 로빈스, 모건 프리먼 등이 주연한 영화 \"쇼생크 탈출\"(프랭크 다라본트, 1999)은 은행가인 앤디 듀프레인이 아내와 그녀의 정부를 살해했다는 누명으로 종신형을 선고받고 수감되었지만 결국 교도소장의 비리를 밝혀내고 탈출하는 이야기가 중심 줄거리입니다.\n\n익숙한 세상\n\n주인공 듀프레인이 수감된 쇼생크 감옥은 수감자 거의 대부분이 종신형이나 사형수들이었습니다. 그들 중에는 젊은 시절 쇼생크 감옥에 와서 50년을 복역하였고 지금은 노인이 된 브룩스라는 사람이 있었습니다. 그런데 그가 50년 동안 모범수로 복역했기에 교도소는 그의 수감을 정지시키고 출감시키기로 결정합니다. 그 소식을 들은 그때부터 브룩스는 불안한 증상을 보입니다. 급기야 브룩스는 한 동료를 칼삼고 칼을 들이대고 인질극을 벌입니다. 놀랍게도 브룩스가 그렇게 행동한 것은 감옥에 남기 위해서였습니다. 감옥 밖이 불안했던 것입니다. 50년동안 감옥에 있으면서 감옥 도서관에서 일하던 브룩스에게 쇼생크 밖 세상은 낯선 곳이었기 때문입니다. 이같은 반응에 동료 수감자들은 그가 미쳤다고 생각합니다. 하지만 브룩스가 그렇게 행동한 것은 모두가 형오하는 감옥에 남기 위해서였습니다. 원래 자유로운 몸이고 희망으로 사는 것이 무엇인지, 그 의미를 잃어버린 것입니다. 왜 이렇게 된 것입니까? 그의 동료 레드(모건 프리먼)의 애기가 잘 기억났습니다.\n\n\"브룩스는 미친 것이 아니. 교도소에 길들여진 것 뿐이야.(He's just institutionalized) 50년을 있어봐. 바깥 세상을 몰라. 여기선 그가 대장이야.. 모르는 게 없지. 하지만 사회에선 아무 것도 아냐. 쓸모없는 쓰레기지... 이 철책이 웃기지. 처음에는 거부하려하지만 곧 익숙해져가. 그리고 세월이 지나면 벗어날 수 없게 되지. 그게 길들여지는거야.\"\n\n길들여졌다(institutionalized). 길들여진 것입니다. 감옥이, 지금 그 상황이 익숙하고 편해진 것입니다.\n\n\"처음에는 거부하려하지만 곧 익숙해져가.\"\n\n참 놀라운 말입니다. 익숙해져서 길들여진다는 것! 정말 무섭습니다. 왜냐하면 정작 그 감옥이 진실로 여겨지기 때문입니다. 분명 감옥이지만 길들여지자 그 감옥이 편하고 자연스러워지는 것입니다. 그 곳이 감옥이"
          }
        ]
      },
      {
        "pageLabel": "1w2p",
        "blocks": [
          {
            "type": "text",
            "content": "어도 상관없습니다. 길들여지지 그 감옥이 자연스러운 일상이 된 것입니다. 그래도 나와야 했던 세상, 기막힌 일이 벌어집니다. 처음부터 어색함이 다가옵니다. 아니, 어색함을 넘어 적응이 되지 않았습니다. 자유롭게 살아야 할 세상이 오히려 그에게는 견딜 수 없는 감옥으로 다가온 것입니다. 적응할 수 없었습니다. 결국 그가 택한 것은 이 세상으로부터의 탈출, 곧 죽음이었습니다. 자신이 살던 아파트 문설주에 이렇게 한 줄의 글을 남기고 말입니다."
          },
          {
            "type": "text",
            "content": "'Brooks was here.'(브룩스 여기에 있었다)"
          },
          {
            "type": "text",
            "content": "원래 브룩스가 살아야 했던 곳은 자유와 기회가 있는 쇼생크 밖 세상입니다. 그런데 브룩스에게 익숙한 세상은 쇼생크 교도소 안이었습니다. 억압과 구속 그리고 모든 것이 통제된 세상에서 50년을 살다보니 그 세상이 익숙해진 것입니다. 쇼생크 밖이 부자연스럽고 두려운 세상이 된 것입니다. 자유가 어색하고 불안한 이유였고 그가 생을 포기한 이유였습니다."
          },
          {
            "type": "text",
            "content": "의심하지 않는다"
          },
          {
            "type": "text",
            "content": "우리 역시 그 시스템 아래서 살고 있습니다. 그런데 매우 자연스럽게 여깁니다. 이유는 간단합니다. 우리가 그동안 살아온 세상이기 때문입니다. 익숙한 것입니다. 그저 이 세상에서 늘 살아왔기 때문에 속절없이 죄어진 세상의 논리를 따라 아무 의심 없이 삽니다.\n그렇다면 왜 의심하거나 질문하지 않는 것입니까? 물론 의심할 때도 있겠지만 그래도 그대로 지나가는 이유는 쇼생크 감옥의 브룩스처럼 익숙해졌기 때문입니다. 그리고 우리는 이 땅에 태어나 살 때 어떻게 살 것인지 그렇게 심각하게 고민하지 않습니다. 그렇게 여행을 시작합니다."
          },
          {
            "type": "text",
            "content": "우리는 본명 스스로 자신이 결정하여 가고 있고 살고 있지만 사실은 세상이 정해놓은 원리대로 살고 있는 것이 진실입니다. 소위 악독갑식, 적자생존, 자연도태가 생존원리에 지배를 받습니다. 그렇게 태어나면서부터 우리는 스스로 결정할 수 없는 틀니바퀴 같은 삶으로 들어섭니다. 사람들이 걸어간다 그 길을 좇아 갑니다."
          }
        ]
      },
      {
        "pageLabel": "1w3p",
        "blocks": [
          {
            "type": "text",
            "content": "정말 열심히 삽니다. 어린이 집, 유치원에 들어가면서부터 과외 2-3개는 기본으로 합니다. 세상에서의 들나바퀴 같은 삶이 시작된 것입니다. 초등학교, 중학교, 대학교 그리고 취업할 때까지 열심히 삽니다. 우리 아이들은 어느 시대보다 열심히 공부하고 학교, 학원, 방송과외로 몸부림치며 부지런히 삽니다."
          },
          {
            "type": "text",
            "content": "이 세상에서 사람들의 전력질주하는 모습은 꽃처럼 아름다워 보입니다. 나의 열심 역시 결국은 그같은 아름다움에 이를 것이라고 생각하여 열심을 냅니다."
          },
          {
            "type": "text",
            "content": "이렇게 열심히 살면 세상 사람들이 이른 성공의 기쁨, 돈과 권력과 풍요와 쾌락 그리고 명예와 영광이 주어질 것을 기대합니다. 그것이 꿈이 됩니다. 예수를 믿는 이유가 되기도 합니다."
          },
          {
            "type": "text",
            "content": "많은 사람들이 자신들이 경해놓은 꿈을 이루지 못합니다. 소위 성공한 사람들조차도 자신이 잘 살았다고 생각하지 않습니다."
          },
          {
            "type": "text",
            "content": "*묵상질문\n그동안 살아온 자신의 인생을 돌아보십시오. 아마 열심히 살았을 것입니다. 그런데 어떻습니까? 기대했던 꿈을 이루셨습니까? 그동안의 삶이 만족할만한 삶이었습니까?"
          }
        ]
      },
      {
        "pageLabel": "1w4p",
        "blocks": [
          {
            "type": "text",
            "content": "분명 그동안 살아온 삶이 쉽지 않았을 것입니다. 그럼에도 불구하고 우리는 이같은 삶을 지속하는 것입니다. 그것은 소생크 감옥에 살던 브룩스처럼 지금 주어진 삶이 전부라고 여기기 때문입니다."
          },
          {
            "type": "text",
            "content": "하지만 성경은 조금은 다른 대답을 합니다. 성경은 우리가 \"허물과 죄로 죽었던\"(엡2:1) 사람들이라고 먼저 말합니다. 죽었다! 죽은 존재라는 말입니다. 출리가는 대로 산다는 뜻입니다. 마치 죽은 물고기가 물이 흐르는 대로 움직이듯이 스스로 무엇을 결정할 수 없는 상태로 삽니다. 이 세상 방식대로, 출리가는 대로 살아왔고 삽니다. 성경이 말하는 우리의 삶입니다."
          },
          {
            "type": "text",
            "content": "\"여러분도 전에는 허물과 죄로 죽었던 사람들입니다. 그 때에 여러분은 허물과 죄 가운데서, 이 세상의 풍조를 따라 살고, 공중의 권세를 잡은 통치자, 곧 지금 불순종의 자식들 가운데서 작용하는 영을 따라 살았습니다.\"(새번역/ 에베서 2:1-2)"
          },
          {
            "type": "text",
            "content": "•묵상질문\n잘 생각해보십시오. 그동안 나의 삶은 내가 주도적으로 계획하며 살아온 삶입니까? 아니면 사람들이 걷어온 길을 좇아서 살아온 삶입니까? 분명한 것은 미래도 사람들이 걸었던 삶을 살다가 끝날 것입니다. 그렇지 않습니까?"
          }
        ]
      }
    ],
    "allBlocks": [
      {
        "type": "text",
        "content": "01 믿음이 필요한 이유\n인생(人生)\n\n팀 로빈스, 모건 프리먼 등이 주연한 영화 \"쇼생크 탈출\"(프랭크 다라본트, 1999)은 은행가인 앤디 듀프레인이 아내와 그녀의 정부를 살해했다는 누명으로 종신형을 선고받고 수감되었지만 결국 교도소장의 비리를 밝혀내고 탈출하는 이야기가 중심 줄거리입니다.\n\n익숙한 세상\n\n주인공 듀프레인이 수감된 쇼생크 감옥은 수감자 거의 대부분이 종신형이나 사형수들이었습니다. 그들 중에는 젊은 시절 쇼생크 감옥에 와서 50년을 복역하였고 지금은 노인이 된 브룩스라는 사람이 있었습니다. 그런데 그가 50년 동안 모범수로 복역했기에 교도소는 그의 수감을 정지시키고 출감시키기로 결정합니다. 그 소식을 들은 그때부터 브룩스는 불안한 증상을 보입니다. 급기야 브룩스는 한 동료를 칼삼고 칼을 들이대고 인질극을 벌입니다. 놀랍게도 브룩스가 그렇게 행동한 것은 감옥에 남기 위해서였습니다. 감옥 밖이 불안했던 것입니다. 50년동안 감옥에 있으면서 감옥 도서관에서 일하던 브룩스에게 쇼생크 밖 세상은 낯선 곳이었기 때문입니다. 이같은 반응에 동료 수감자들은 그가 미쳤다고 생각합니다. 하지만 브룩스가 그렇게 행동한 것은 모두가 형오하는 감옥에 남기 위해서였습니다. 원래 자유로운 몸이고 희망으로 사는 것이 무엇인지, 그 의미를 잃어버린 것입니다. 왜 이렇게 된 것입니까? 그의 동료 레드(모건 프리먼)의 애기가 잘 기억났습니다.\n\n\"브룩스는 미친 것이 아니. 교도소에 길들여진 것 뿐이야.(He's just institutionalized) 50년을 있어봐. 바깥 세상을 몰라. 여기선 그가 대장이야.. 모르는 게 없지. 하지만 사회에선 아무 것도 아냐. 쓸모없는 쓰레기지... 이 철책이 웃기지. 처음에는 거부하려하지만 곧 익숙해져가. 그리고 세월이 지나면 벗어날 수 없게 되지. 그게 길들여지는거야.\"\n\n길들여졌다(institutionalized). 길들여진 것입니다. 감옥이, 지금 그 상황이 익숙하고 편해진 것입니다.\n\n\"처음에는 거부하려하지만 곧 익숙해져가.\"\n\n참 놀라운 말입니다. 익숙해져서 길들여진다는 것! 정말 무섭습니다. 왜냐하면 정작 그 감옥이 진실로 여겨지기 때문입니다. 분명 감옥이지만 길들여지자 그 감옥이 편하고 자연스러워지는 것입니다. 그 곳이 감옥이"
      },
      {
        "type": "text",
        "content": "어도 상관없습니다. 길들여지지 그 감옥이 자연스러운 일상이 된 것입니다. 그래도 나와야 했던 세상, 기막힌 일이 벌어집니다. 처음부터 어색함이 다가옵니다. 아니, 어색함을 넘어 적응이 되지 않았습니다. 자유롭게 살아야 할 세상이 오히려 그에게는 견딜 수 없는 감옥으로 다가온 것입니다. 적응할 수 없었습니다. 결국 그가 택한 것은 이 세상으로부터의 탈출, 곧 죽음이었습니다. 자신이 살던 아파트 문설주에 이렇게 한 줄의 글을 남기고 말입니다."
      },
      {
        "type": "text",
        "content": "'Brooks was here.'(브룩스 여기에 있었다)"
      },
      {
        "type": "text",
        "content": "원래 브룩스가 살아야 했던 곳은 자유와 기회가 있는 쇼생크 밖 세상입니다. 그런데 브룩스에게 익숙한 세상은 쇼생크 교도소 안이었습니다. 억압과 구속 그리고 모든 것이 통제된 세상에서 50년을 살다보니 그 세상이 익숙해진 것입니다. 쇼생크 밖이 부자연스럽고 두려운 세상이 된 것입니다. 자유가 어색하고 불안한 이유였고 그가 생을 포기한 이유였습니다."
      },
      {
        "type": "text",
        "content": "의심하지 않는다"
      },
      {
        "type": "text",
        "content": "우리 역시 그 시스템 아래서 살고 있습니다. 그런데 매우 자연스럽게 여깁니다. 이유는 간단합니다. 우리가 그동안 살아온 세상이기 때문입니다. 익숙한 것입니다. 그저 이 세상에서 늘 살아왔기 때문에 속절없이 죄어진 세상의 논리를 따라 아무 의심 없이 삽니다.\n그렇다면 왜 의심하거나 질문하지 않는 것입니까? 물론 의심할 때도 있겠지만 그래도 그대로 지나가는 이유는 쇼생크 감옥의 브룩스처럼 익숙해졌기 때문입니다. 그리고 우리는 이 땅에 태어나 살 때 어떻게 살 것인지 그렇게 심각하게 고민하지 않습니다. 그렇게 여행을 시작합니다."
      },
      {
        "type": "text",
        "content": "우리는 본명 스스로 자신이 결정하여 가고 있고 살고 있지만 사실은 세상이 정해놓은 원리대로 살고 있는 것이 진실입니다. 소위 악독갑식, 적자생존, 자연도태가 생존원리에 지배를 받습니다. 그렇게 태어나면서부터 우리는 스스로 결정할 수 없는 틀니바퀴 같은 삶으로 들어섭니다. 사람들이 걸어간다 그 길을 좇아 갑니다."
      },
      {
        "type": "text",
        "content": "정말 열심히 삽니다. 어린이 집, 유치원에 들어가면서부터 과외 2-3개는 기본으로 합니다. 세상에서의 들나바퀴 같은 삶이 시작된 것입니다. 초등학교, 중학교, 대학교 그리고 취업할 때까지 열심히 삽니다. 우리 아이들은 어느 시대보다 열심히 공부하고 학교, 학원, 방송과외로 몸부림치며 부지런히 삽니다."
      },
      {
        "type": "text",
        "content": "이 세상에서 사람들의 전력질주하는 모습은 꽃처럼 아름다워 보입니다. 나의 열심 역시 결국은 그같은 아름다움에 이를 것이라고 생각하여 열심을 냅니다."
      },
      {
        "type": "text",
        "content": "이렇게 열심히 살면 세상 사람들이 이른 성공의 기쁨, 돈과 권력과 풍요와 쾌락 그리고 명예와 영광이 주어질 것을 기대합니다. 그것이 꿈이 됩니다. 예수를 믿는 이유가 되기도 합니다."
      },
      {
        "type": "text",
        "content": "많은 사람들이 자신들이 경해놓은 꿈을 이루지 못합니다. 소위 성공한 사람들조차도 자신이 잘 살았다고 생각하지 않습니다."
      },
      {
        "type": "text",
        "content": "*묵상질문\n그동안 살아온 자신의 인생을 돌아보십시오. 아마 열심히 살았을 것입니다. 그런데 어떻습니까? 기대했던 꿈을 이루셨습니까? 그동안의 삶이 만족할만한 삶이었습니까?"
      },
      {
        "type": "text",
        "content": "분명 그동안 살아온 삶이 쉽지 않았을 것입니다. 그럼에도 불구하고 우리는 이같은 삶을 지속하는 것입니다. 그것은 소생크 감옥에 살던 브룩스처럼 지금 주어진 삶이 전부라고 여기기 때문입니다."
      },
      {
        "type": "text",
        "content": "하지만 성경은 조금은 다른 대답을 합니다. 성경은 우리가 \"허물과 죄로 죽었던\"(엡2:1) 사람들이라고 먼저 말합니다. 죽었다! 죽은 존재라는 말입니다. 출리가는 대로 산다는 뜻입니다. 마치 죽은 물고기가 물이 흐르는 대로 움직이듯이 스스로 무엇을 결정할 수 없는 상태로 삽니다. 이 세상 방식대로, 출리가는 대로 살아왔고 삽니다. 성경이 말하는 우리의 삶입니다."
      },
      {
        "type": "text",
        "content": "\"여러분도 전에는 허물과 죄로 죽었던 사람들입니다. 그 때에 여러분은 허물과 죄 가운데서, 이 세상의 풍조를 따라 살고, 공중의 권세를 잡은 통치자, 곧 지금 불순종의 자식들 가운데서 작용하는 영을 따라 살았습니다.\"(새번역/ 에베서 2:1-2)"
      },
      {
        "type": "text",
        "content": "•묵상질문\n잘 생각해보십시오. 그동안 나의 삶은 내가 주도적으로 계획하며 살아온 삶입니까? 아니면 사람들이 걷어온 길을 좇아서 살아온 삶입니까? 분명한 것은 미래도 사람들이 걸었던 삶을 살다가 끝날 것입니다. 그렇지 않습니까?"
      }
    ],
    "questions": [
      {
        "q": "그동안 살아온 자신의 인생을 돌아보십시오. 아마 열심히 살았을 것입니다. 그런데 어떻습니까? 기대했던 꿈을 이루셨습니까? 그동안의 삶이 만족할만한 삶이었습니까?",
        "a": "기대했던 꿈을 이루지 못했습니다.\n비전이라고 생각했던 것도 이루지 못했습니다.\n지금은 다른 목적과 꿈을 보고 살아가고 있습니다."
      },
      {
        "q": "잘 생각해보십시오. 그동안 나의 삶은 내가 주도적으로 계획하며 살아온 삶입니까? 아니면 사람들이 걸어온 길을 좇아서 살아온 삶입니까? 분명한 것은 미래도 사람들이 걸었던 삶을 살다가 끝날 것입니다. 그렇지 않습니까?",
        "a": "남들이 걸어간 길을 걷다가 주도적인 길을 걷다가. 또 아니다가. 다시 그러다가. 계속 왔다갔다했던 것 같습니다.\n"
      }
    ]
  }
]